asyncio_taskpool/__init__.py
asyncio_taskpool/exceptions.py
asyncio_taskpool/pool.py
asyncio_taskpool/py.typed
asyncio_taskpool/queue_context.py
asyncio_taskpool/control/__init__.py
asyncio_taskpool/control/__main__.py
asyncio_taskpool/control/client.py
asyncio_taskpool/control/parser.py
asyncio_taskpool/control/server.py
asyncio_taskpool/control/session.py
asyncio_taskpool/internals/__init__.py
asyncio_taskpool/internals/constants.py
asyncio_taskpool/internals/group_register.py
asyncio_taskpool/internals/helpers.py
asyncio_taskpool/internals/types.py
asyncio_taskpool-1.2.0.dist-info/COPYING
asyncio_taskpool-1.2.0.dist-info/COPYING.LESSER
asyncio_taskpool-1.2.0.dist-info/METADATA
asyncio_taskpool-1.2.0.dist-info/WHEEL
asyncio_taskpool-1.2.0.dist-info/top_level.txt
asyncio_taskpool-1.2.0.dist-info/RECORD
