Metadata-Version: 2.1
Name: asyncio-taskpool
Version: 1.2.0
Summary: Dynamically manage pools of asyncio tasks
Author-email: Daniil Fajnberg <mail@daniil.fajnberg.de>
Maintainer-email: Daniil Fajnberg <mail@daniil.fajnberg.de>
License: GNU Lesser General Public License v3 (LGPLv3)
Project-URL: Repository, https://github.com/daniil-berg/asyncio-taskpool
Project-URL: Issue Tracker, https://github.com/daniil-berg/asyncio-taskpool/issues
Project-URL: Documentation, https://asyncio-taskpool.readthedocs.io/en/latest
Keywords: asyncio,concurrency,coroutines,server,tasks
Classifier: Development Status :: 5 - Production/Stable
Classifier: Programming Language :: Python :: 3 :: Only
Classifier: Programming Language :: Python :: 3.8
Classifier: Programming Language :: Python :: 3.9
Classifier: Programming Language :: Python :: 3.10
Classifier: Programming Language :: Python :: 3.11
Classifier: Operating System :: OS Independent
Classifier: License :: OSI Approved :: GNU Lesser General Public License v3 (LGPLv3)
Classifier: Intended Audience :: Developers
Classifier: Intended Audience :: System Administrators
Classifier: Framework :: AsyncIO
Classifier: Topic :: Software Development :: Libraries
Classifier: Topic :: Software Development :: Libraries :: Python Modules
Requires-Python: <4.0,>=3.8
License-File: COPYING
License-File: COPYING.LESSER
Provides-Extra: dev
Requires-Dist: black ==23.9.1 ; extra == 'dev'
Requires-Dist: build ==1.0.3 ; extra == 'dev'
Requires-Dist: coverage[toml] ==7.3.2 ; extra == 'dev'
Requires-Dist: isort ==5.12.0 ; extra == 'dev'
Requires-Dist: mypy ==1.5.1 ; extra == 'dev'
Requires-Dist: ruff ==0.0.292 ; extra == 'dev'
Requires-Dist: sphinx ==7.1.2 ; extra == 'dev'
Requires-Dist: sphinx-rtd-theme ==1.3.0 ; extra == 'dev'
